rtl/pe.v
module pe (
    input logic clk,
    input logic rst,

    input logic [7:0] a_in,
    input logic [7:0] b_in,

    output logic [7:0] a_out,
    output logic [7:0] b_out,
    
    output logic [31:0] result_out // we are doing sum + product which will exceed the 16 bits hence using the 32 bits
);
    
// logic [31:0] product;
always_ff @(posedge clk or posedge rst) begin

    if (rst) begin 
        a_out <= 8'b0; //assign a and b to 0 on reset
        b_out <= 8'b0;
        result_out <= 32'b0; //new sum = old sum + product, hence old sum = 0
    end 
    
    else begin
        a_out <= a_in;
        b_out <= b_in;
        // product <= a_in * b_in; // calculate the product
        result_out <= result_out + (a_in * b_in); // sum + product
    end
end
endmodule

rtl/systolic_array.v
module systolic_array (
    input logic clk, rst,

    input logic [7:0] a0, a1, a2, a3, // inputs to the first rows of PEs
    input logic [7:0] b0, b1, b2, b3, // inputs to the first columns of PEs

    output logic [31:0] result00, result01, result02, result03, // outputs of the first row of PEs  
    output logic [31:0] result10, result11, result12, result13, // outputs of the second row of PEs
    output logic [31:0] result20, result21, result22, result23,
    output logic [31:0] result30, result31, result32, result33
);

//wires to connect inside the array of PEs
logic [7:0] a00, a01, a02, a03; // for row 0
logic [7:0] a10, a11, a12, a13; // for row 1 
logic [7:0] a20, a21, a22, a23; // for row 2
logic [7:0] a30, a31, a32, a33; // for row 3        

logic [7:0] b00, b01, b02, b03; // for column 0
logic [7:0] b10, b11, b12, b13; // for column 1
logic [7:0] b20, b21, b22, b23; // for column 2
logic [7:0] b30, b31, b32, b33; // for column 3

// ROW 0 Col 0
pe pe00 (
    .clk(clk),
    .rst(rst),
    .a_in(a0), // input from outside
    .b_in(b0), // input from outside
    .a_out(a00), // output to the right
    .b_out(b00), // output downwards
    .result_out(result00) // output result
);
// ROW 0 Col 1
pe pe01 (
    .clk(clk),
    .rst(rst),
    .a_in(a00), // input from the left PE
    .b_in(b1), // input from outside
    .a_out(a01), // output to the right
    .b_out(b01), // output downwards
    .result_out(result01) // output result
);
// ROW 0 Col 2
pe pe02 (
    .clk(clk),
    .rst(rst),
    .a_in(a01), // input from the left PE
    .b_in(b2), // input from outside
    .a_out(a02), // output to the right
    .b_out(b02), // output downwards
    .result_out(result02) // output result
);
// ROW 0 Col 3
pe pe03 (
    .clk(clk),
    .rst(rst),
    .a_in(a02), // input from the left PE
    .b_in(b3), // input from outside
    .a_out(a03), // output to the right
    .b_out(b03), // output downwards
    .result_out(result03) // output result
);  
// ROW 1 Col 0
pe pe10 (
    .clk(clk),
    .rst(rst),
    .a_in(a1), // input from outside
    .b_in(b00), // input from the top PE
    .a_out(a10), // output to the right
    .b_out(b10), // output downwards
    .result_out(result10) // output result
);
// ROW 1 Col 1
pe pe11 (
    .clk(clk),
    .rst(rst),
    .a_in(a10), // input from the left PE
    .b_in(b01), // input from the top PE
    .a_out(a11), // output to the right
    .b_out(b11), // output downwards
    .result_out(result11) // output result
);
// ROW 1 Col 2
pe pe12 (
    .clk(clk),
    .rst(rst),
    .a_in(a11), // input from the left PE
    .b_in(b02), // input from the top PE
    .a_out(a12), // output to the right
    .b_out(b12), // output downwards
    .result_out(result12) // output result
);
// ROW 1 Col 3
pe pe13 (
    .clk(clk),
    .rst(rst),
    .a_in(a12), // input from the left PE
    .b_in(b03), // input from the top PE
    .a_out(a13), // output to the right
    .b_out(b13), // output downwards
    .result_out(result13) // output result
);
// ROW 2 Col 0
pe pe20 (
    .clk(clk),
    .rst(rst),
    .a_in(a2), // input from outside
    .b_in(b10), // input from the top PE
    .a_out(a20), // output to the right
    .b_out(b20), // output downwards
    .result_out(result20) // output result
);
// ROW 2 Col 1
pe pe21 (
    .clk(clk),
    .rst(rst),
    .a_in(a20), // input from the left PE
    .b_in(b11), // input from the top PE
    .a_out(a21), // output to the right
    .b_out(b21), // output downwards
    .result_out(result21) // output result
);
// ROW 2 Col 2
pe pe22 (
    .clk(clk),
    .rst(rst),
    .a_in(a21), // input from the left PE
    .b_in(b12), // input from the top PE
    .a_out(a22), // output to the right
    .b_out(b22), // output downwards
    .result_out(result22) // output result
);
// ROW 2 Col 3
pe pe23 (
    .clk(clk),
    .rst(rst),
    .a_in(a22), // input from the left PE
    .b_in(b13), // input from the top PE
    .a_out(a23), // output to the right
    .b_out(b23), // output downwards
    .result_out(result23) // output result
);
// ROW 3 Col 0
pe pe30 (
    .clk(clk),
    .rst(rst),
    .a_in(a3), // input from outside
    .b_in(b20), // input from the top PE
    .a_out(a30), // output to the right
    .b_out(b30), // output downwards
    .result_out(result30) // output result
);
// ROW 3 Col 1
pe pe31 (
    .clk(clk),
    .rst(rst),
    .a_in(a30), // input from the left PE
    .b_in(b21), // input from the top PE
    .a_out(a31), // output to the right
    .b_out(b31), // output downwards
    .result_out(result31) // output result
);
// ROW 3 Col 2
pe pe32 (
    .clk(clk),
    .rst(rst),
    .a_in(a31), // input from the left PE
    .b_in(b22), // input from the top PE
    .a_out(a32), // output to the right
    .b_out(b32), // output downwards
    .result_out(result32) // output result
);
// ROW 3 Col 3
pe pe33 (
    .clk(clk),
    .rst(rst),
    .a_in(a32), // input from the left PE
    .b_in(b23), // input from the top PE
    .a_out(a33), // output to the right
    .b_out(b33), // output downwards
    .result_out(result33) // output result
);
    
endmodule

rtl/systolic_tb_4x4.v
`timescale 1ns / 1ps
module systolic_tb_4x4;

    logic rst, clk;
    logic [7:0] a0, a1, a2, a3; // rows of PEs
    logic [7:0] b0, b1, b2, b3; // columns of PEs

    logic [31:0] result00, result01, result02, result03;
    logic [31:0] result10, result11, result12, result13;
    logic [31:0] result20, result21, result22, result23;
    logic [31:0] result30, result31, result32, result33;    

    systolic_array dut (
        .clk(clk),
        .rst(rst),
        .a0(a0),
        .a1(a1),
        .a2(a2),
        .a3(a3),
        .b0(b0),
        .b1(b1),
        .b2(b2),
        .b3(b3),
        .result00(result00), .result01(result01), .result02(result02), .result03(result03),
        .result10(result10), .result11(result11), .result12(result12), .result13(result13),
        .result20(result20), .result21(result21), .result22(result22), .result23(result23),
        .result30(result30), .result31(result31), .result32(result32), .result33(result33)
    );

    always #5 clk = ~clk;
initial begin
        $dumpfile("systolic_4x4.vcd");
        $dumpvars(0, systolic_tb_4x4);
        clk = 0;
        rst = 1;
        a0 = 0; a1 = 0; a2 = 0; a3 = 0;
        b0 = 0; b1 = 0; b2 = 0; b3 = 0; 

        #20;
        rst = 0;
        $display("--- Starting 4x4 Matrix Multiplication Test ---");
        
        // --- IMPORTANT: WAIT FOR CLOCK EDGE BEFORE DRIVING INPUTS ---
        @(posedge clk); 

        // Cycle 1
        a0 <= 1; b0 <= 2; 
        @(posedge clk); 

        // Cycle 2
        a0 <= 1; b0 <= 2; 
        a1 <= 1; b1 <= 2;
        @(posedge clk); 

        // Cycle 3
        a0 <= 1; b0 <= 2; 
        a1 <= 1; b1 <= 2; 
        a2 <= 1; b2 <= 2;
        @(posedge clk); 

        // Cycle 4
        a0 <= 1; b0 <= 2; 
        a1 <= 1; b1 <= 2; 
        a2 <= 1; b2 <= 2; 
        a3 <= 1; b3 <= 2; 
        @(posedge clk); 

        // Cycle 5 (Row 0 Done)
        a0 <= 0; b0 <= 0; 
        a1 <= 1; b1 <= 2; 
        a2 <= 1; b2 <= 2; 
        a3 <= 1; b3 <= 2; 
        @(posedge clk); 

        // Cycle 6
        a1 <= 0; b1 <= 0;
        a2 <= 1; b2 <= 2; 
        a3 <= 1; b3 <= 2;   
        @(posedge clk); 

        // Cycle 7
        a2 <= 0; b2 <= 0;
        a3 <= 1; b3 <= 2;   
        @(posedge clk); 

        // Cycle 8
        a3 <= 0; b3 <= 0;
        @(posedge clk); 

        // Wait for results to propagate
        repeat (10) @(posedge clk); 

        // Check Results
        if (result00 == 8 && result03 == 8 && result30 == 8 && result33 == 8) 
            $display("PASS: All corners are 8.");
        else 
            $display("FAIL: Expected 8. Got R00=%d R33=%d", result00, result33);
            
        $display("\nResult Matrix:");
        $display("%d %d %d %d", result00, result01, result02, result03);
        $display("%d %d %d %d", result10, result11, result12, result13);
        $display("%d %d %d %d", result20, result21, result22, result23);
        $display("%d %d %d %d", result30, result31, result32, result33);

        $finish;
    end
endmodule

rtl/systolic_4x4.vcd
$date
	Tue Feb 10 23:50:09 2026
$end
$version
	Icarus Verilog
$end
$timescale
	1ps
$end
$scope module systolic_tb_4x4 $end
$var wire 32 ! result33 [31:0] $end
$var wire 32 " result32 [31:0] $end
$var wire 32 # result31 [31:0] $end
$var wire 32 $ result30 [31:0] $end
$var wire 32 % result23 [31:0] $end
$var wire 32 & result22 [31:0] $end
$var wire 32 ' result21 [31:0] $end
$var wire 32 ( result20 [31:0] $end
$var wire 32 ) result13 [31:0] $end
$var wire 32 * result12 [31:0] $end
$var wire 32 + result11 [31:0] $end
$var wire 32 , result10 [31:0] $end
$var wire 32 - result03 [31:0] $end
$var wire 32 . result02 [31:0] $end
$var wire 32 / result01 [31:0] $end
$var wire 32 0 result00 [31:0] $end
$var reg 8 1 a0 [7:0] $end
$var reg 8 2 a1 [7:0] $end
$var reg 8 3 a2 [7:0] $end
$var reg 8 4 a3 [7:0] $end
$var reg 8 5 b0 [7:0] $end
$var reg 8 6 b1 [7:0] $end
$var reg 8 7 b2 [7:0] $end
$var reg 8 8 b3 [7:0] $end
$var reg 1 9 clk $end
$var reg 1 : rst $end
$scope module dut $end
$var wire 8 ; a0 [7:0] $end
$var wire 8 < a1 [7:0] $end
$var wire 8 = a2 [7:0] $end
$var wire 8 > a3 [7:0] $end
$var wire 8 ? b0 [7:0] $end
$var wire 8 @ b1 [7:0] $end
$var wire 8 A b2 [7:0] $end
$var wire 8 B b3 [7:0] $end
$var wire 1 9 clk $end
$var wire 1 : rst $end
$var wire 32 C result33 [31:0] $end
$var wire 32 D result32 [31:0] $end
$var wire 32 E result31 [31:0] $end
$var wire 32 F result30 [31:0] $end
$var wire 32 G result23 [31:0] $end
$var wire 32 H result22 [31:0] $end
$var wire 32 I result21 [31:0] $end
$var wire 32 J result20 [31:0] $end
$var wire 32 K result13 [31:0] $end
$var wire 32 L result12 [31:0] $end
$var wire 32 M result11 [31:0] $end
$var wire 32 N result10 [31:0] $end
$var wire 32 O result03 [31:0] $end
$var wire 32 P result02 [31:0] $end
$var wire 32 Q result01 [31:0] $end
$var wire 32 R result00 [31:0] $end
$var wire 8 S b33 [7:0] $end
$var wire 8 T b32 [7:0] $end
$var wire 8 U b31 [7:0] $end
$var wire 8 V b30 [7:0] $end
$var wire 8 W b23 [7:0] $end
$var wire 8 X b22 [7:0] $end
$var wire 8 Y b21 [7:0] $end
$var wire 8 Z b20 [7:0] $end
$var wire 8 [ b13 [7:0] $end
$var wire 8 \ b12 [7:0] $end
$var wire 8 ] b11 [7:0] $end
$var wire 8 ^ b10 [7:0] $end
$var wire 8 _ b03 [7:0] $end
$var wire 8 ` b02 [7:0] $end
$var wire 8 a b01 [7:0] $end
$var wire 8 b b00 [7:0] $end
$var wire 8 c a33 [7:0] $end
$var wire 8 d a32 [7:0] $end
$var wire 8 e a31 [7:0] $end
$var wire 8 f a30 [7:0] $end
$var wire 8 g a23 [7:0] $end
$var wire 8 h a22 [7:0] $end
$var wire 8 i a21 [7:0] $end
$var wire 8 j a20 [7:0] $end
$var wire 8 k a13 [7:0] $end
$var wire 8 l a12 [7:0] $end
$var wire 8 m a11 [7:0] $end
$var wire 8 n a10 [7:0] $end
$var wire 8 o a03 [7:0] $end
$var wire 8 p a02 [7:0] $end
$var wire 8 q a01 [7:0] $end
$var wire 8 r a00 [7:0] $end
$scope module pe00 $end
$var wire 8 s a_in [7:0] $end
$var wire 8 t b_in [7:0] $end
$var wire 1 9 clk $end
$var wire 1 : rst $end
$var reg 8 u a_out [7:0] $end
$var reg 8 v b_out [7:0] $end
$var reg 32 w result_out [31:0] $end
$upscope $end
$scope module pe01 $end
$var wire 8 x a_in [7:0] $end
$var wire 8 y b_in [7:0] $end
$var wire 1 9 clk $end
$var wire 1 : rst $end
$var reg 8 z a_out [7:0] $end
$var reg 8 { b_out [7:0] $end
$var reg 32 | result_out [31:0] $end
$upscope $end
$scope module pe02 $end
$var wire 8 } a_in [7:0] $end
$var wire 8 ~ b_in [7:0] $end
$var wire 1 9 clk $end
$var wire 1 : rst $end
$var reg 8 !" a_out [7:0] $end
$var reg 8 "" b_out [7:0] $end
$var reg 32 #" result_out [31:0] $end
$upscope $end
$scope module pe03 $end
$var wire 8 $" a_in [7:0] $end
$var wire 8 %" b_in [7:0] $end
$var wire 1 9 clk $end
$var wire 1 : rst $end
$var reg 8 &" a_out [7:0] $end
$var reg 8 '" b_out [7:0] $end
$var reg 32 (" result_out [31:0] $end
$upscope $end
$scope module pe10 $end
$var wire 8 )" a_in [7:0] $end
$var wire 8 *" b_in [7:0] $end
$var wire 1 9 clk $end
$var wire 1 : rst $end
$var reg 8 +" a_out [7:0] $end
$var reg 8 ," b_out [7:0] $end
$var reg 32 -" result_out [31:0] $end
$upscope $end
$scope module pe11 $end
$var wire 8 ." a_in [7:0] $end
$var wire 8 /" b_in [7:0] $end
$var wire 1 9 clk $end
$var wire 1 : rst $end
$var reg 8 0" a_out [7:0] $end
$var reg 8 1" b_out [7:0] $end
$var reg 32 2" result_out [31:0] $end
$upscope $end
$scope module pe12 $end
$var wire 8 3" a_in [7:0] $end
$var wire 8 4" b_in [7:0] $end
$var wire 1 9 clk $end
$var wire 1 : rst $end
$var reg 8 5" a_out [7:0] $end
$var reg 8 6" b_out [7:0] $end
$var reg 32 7" result_out [31:0] $end
$upscope $end
$scope module pe13 $end
$var wire 8 8" a_in [7:0] $end
$var wire 8 9" b_in [7:0] $end
$var wire 1 9 clk $end
$var wire 1 : rst $end
$var reg 8 :" a_out [7:0] $end
$var reg 8 ;" b_out [7:0] $end
$var reg 32 <" result_out [31:0] $end
$upscope $end
$scope module pe20 $end
$var wire 8 =" a_in [7:0] $end
$var wire 8 >" b_in [7:0] $end
$var wire 1 9 clk $end
$var wire 1 : rst $end
$var reg 8 ?" a_out [7:0] $end
$var reg 8 @" b_out [7:0] $end
$var reg 32 A" result_out [31:0] $end
$upscope $end
$scope module pe21 $end
$var wire 8 B" a_in [7:0] $end
$var wire 8 C" b_in [7:0] $end
$var wire 1 9 clk $end
$var wire 1 : rst $end
$var reg 8 D" a_out [7:0] $end
$var reg 8 E" b_out [7:0] $end
$var reg 32 F" result_out [31:0] $end
$upscope $end
$scope module pe22 $end
$var wire 8 G" a_in [7:0] $end
$var wire 8 H" b_in [7:0] $end
$var wire 1 9 clk $end
$var wire 1 : rst $end
$var reg 8 I" a_out [7:0] $end
$var reg 8 J" b_out [7:0] $end
$var reg 32 K" result_out [31:0] $end
$upscope $end
$scope module pe23 $end
$var wire 8 L" a_in [7:0] $end
$var wire 8 M" b_in [7:0] $end
$var wire 1 9 clk $end
$var wire 1 : rst $end
$var reg 8 N" a_out [7:0] $end
$var reg 8 O" b_out [7:0] $end
$var reg 32 P" result_out [31:0] $end
$upscope $end
$scope module pe30 $end
$var wire 8 Q" a_in [7:0] $end
$var wire 8 R" b_in [7:0] $end
$var wire 1 9 clk $end
$var wire 1 : rst $end
$var reg 8 S" a_out [7:0] $end
$var reg 8 T" b_out [7:0] $end
$var reg 32 U" result_out [31:0] $end
$upscope $end
$scope module pe31 $end
$var wire 8 V" a_in [7:0] $end
$var wire 8 W" b_in [7:0] $end
$var wire 1 9 clk $end
$var wire 1 : rst $end
$var reg 8 X" a_out [7:0] $end
$var reg 8 Y" b_out [7:0] $end
$var reg 32 Z" result_out [31:0] $end
$upscope $end
$scope module pe32 $end
$var wire 8 [" a_in [7:0] $end
$var wire 8 \" b_in [7:0] $end
$var wire 1 9 clk $end
$var wire 1 : rst $end
$var reg 8 ]" a_out [7:0] $end
$var reg 8 ^" b_out [7:0] $end
$var reg 32 _" result_out [31:0] $end
$upscope $end
$scope module pe33 $end
$var wire 8 `" a_in [7:0] $end
$var wire 8 a" b_in [7:0] $end
$var wire 1 9 clk $end
$var wire 1 : rst $end
$var reg 8 b" a_out [7:0] $end
$var reg 8 c" b_out [7:0] $end
$var reg 32 d" result_out [31:0] $end
$upscope $end
$upscope $end
$upscope $end
$enddefinitions $end
$comment Show the parameter values. $end
$dumpall
$end
#0
$dumpvars
b0 d"
b0 c"
b0 b"
b0 a"
b0 `"
b0 _"
b0 ^"
b0 ]"
b0 \"
b0 ["
b0 Z"
b0 Y"
b0 X"
b0 W"
b0 V"
b0 U"
b0 T"
b0 S"
b0 R"
b0 Q"
b0 P"
b0 O"
b0 N"
b0 M"
b0 L"
b0 K"
b0 J"
b0 I"
b0 H"
b0 G"
b0 F"
b0 E"
b0 D"
b0 C"
b0 B"
b0 A"
b0 @"
b0 ?"
b0 >"
b0 ="
b0 <"
b0 ;"
b0 :"
b0 9"
b0 8"
b0 7"
b0 6"
b0 5"
b0 4"
b0 3"
b0 2"
b0 1"
b0 0"
b0 /"
b0 ."
b0 -"
b0 ,"
b0 +"
b0 *"
b0 )"
b0 ("
b0 '"
b0 &"
b0 %"
b0 $"
b0 #"
b0 ""
b0 !"
b0 ~
b0 }
b0 |
b0 {
b0 z
b0 y
b0 x
b0 w
b0 v
b0 u
b0 t
b0 s
b0 r
b0 q
b0 p
b0 o
b0 n
b0 m
b0 l
b0 k
b0 j
b0 i
b0 h
b0 g
b0 f
b0 e
b0 d
b0 c
b0 b
b0 a
b0 `
b0 _
b0 ^
b0 ]
b0 \
b0 [
b0 Z
b0 Y
b0 X
b0 W
b0 V
b0 U
b0 T
b0 S
b0 R
b0 Q
b0 P
b0 O
b0 N
b0 M
b0 L
b0 K
b0 J
b0 I
b0 H
b0 G
b0 F
b0 E
b0 D
b0 C
b0 B
b0 A
b0 @
b0 ?
b0 >
b0 =
b0 <
b0 ;
1:
09
b0 8
b0 7
b0 6
b0 5
b0 4
b0 3
b0 2
b0 1
b0 0
b0 /
b0 .
b0 -
b0 ,
b0 +
b0 *
b0 )
b0 (
b0 '
b0 &
b0 %
b0 $
b0 #
b0 "
b0 !
$end
#5000
19
#10000
09
#15000
19
#20000
09
0:
#25000
b10 5
b10 ?
b10 t
b1 1
b1 ;
b1 s
19
#30000
09
#35000
b10 0
b10 R
b10 w
b10 b
b10 v
b10 *"
b1 r
b1 u
b1 x
b10 6
b10 @
b10 y
b1 2
b1 <
b1 )"
19
#40000
09
#45000
b10 ,
b10 N
b10 -"
b10 ^
b10 ,"
b10 >"
b1 n
b1 +"
b1 ."
b10 /
b10 Q
b10 |
b10 a
b10 {
b10 /"
b1 q
b1 z
b1 }
b100 0
b100 R
b100 w
b10 7
b10 A
b10 ~
b1 3
b1 =
b1 ="
19
#50000
09
#55000
b110 0
b110 R
b110 w
b100 /
b100 Q
b100 |
b10 .
b10 P
b10 #"
b10 `
b10 ""
b10 4"
b1 p
b1 !"
b1 $"
b100 ,
b100 N
b100 -"
b10 +
b10 M
b10 2"
b10 ]
b10 1"
b10 C"
b1 m
b1 0"
b1 3"
b10 (
b10 J
b10 A"
b10 Z
b10 @"
b10 R"
b1 j
b1 ?"
b1 B"
b10 8
b10 B
b10 %"
b1 4
b1 >
b1 Q"
19
#60000
09
#65000
b10 $
b10 F
b10 U"
b10 V
b10 T"
b1 f
b1 S"
b1 V"
b10 '
b10 I
b10 F"
b10 Y
b10 E"
b10 W"
b1 i
b1 D"
b1 G"
b100 (
b100 J
b100 A"
b10 *
b10 L
b10 7"
b10 \
b10 6"
b10 H"
b1 l
b1 5"
b1 8"
b100 +
b100 M
b100 2"
b110 ,
b110 N
b110 -"
b10 -
b10 O
b10 ("
b10 _
b10 '"
b10 9"
b1 o
b1 &"
b100 .
b100 P
b100 #"
b110 /
b110 Q
b110 |
b1000 0
b1000 R
b1000 w
b0 5
b0 ?
b0 t
b0 1
b0 ;
b0 s
19
#70000
09
#75000
b0 b
b0 v
b0 *"
b0 r
b0 u
b0 x
b1000 /
b1000 Q
b1000 |
b110 .
b110 P
b110 #"
b100 -
b100 O
b100 ("
b1000 ,
b1000 N
b1000 -"
b110 +
b110 M
b110 2"
b100 *
b100 L
b100 7"
b10 )
b10 K
b10 <"
b10 [
b10 ;"
b10 M"
b1 k
b1 :"
b110 (
b110 J
b110 A"
b100 '
b100 I
b100 F"
b10 &
b10 H
b10 K"
b10 X
b10 J"
b10 \"
b1 h
b1 I"
b1 L"
b100 $
b100 F
b100 U"
b10 #
b10 E
b10 Z"
b10 U
b10 Y"
b1 e
b1 X"
b1 ["
b0 6
b0 @
b0 y
b0 2
b0 <
b0 )"
19
#80000
09
#85000
b10 "
b10 D
b10 _"
b10 T
b10 ^"
b1 d
b1 ]"
b1 `"
b100 #
b100 E
b100 Z"
b110 $
b110 F
b110 U"
b10 %
b10 G
b10 P"
b10 W
b10 O"
b10 a"
b1 g
b1 N"
b100 &
b100 H
b100 K"
b110 '
b110 I
b110 F"
b1000 (
b1000 J
b1000 A"
b100 )
b100 K
b100 <"
b110 *
b110 L
b110 7"
b1000 +
b1000 M
b1000 2"
b0 ^
b0 ,"
b0 >"
b0 n
b0 +"
b0 ."
b110 -
b110 O
b110 ("
b1000 .
b1000 P
b1000 #"
b0 a
b0 {
b0 /"
b0 q
b0 z
b0 }
b0 7
b0 A
b0 ~
b0 3
b0 =
b0 ="
19
#90000
09
#95000
b0 `
b0 ""
b0 4"
b0 p
b0 !"
b0 $"
b1000 -
b1000 O
b1000 ("
b0 ]
b0 1"
b0 C"
b0 m
b0 0"
b0 3"
b1000 *
b1000 L
b1000 7"
b110 )
b110 K
b110 <"
b0 Z
b0 @"
b0 R"
b0 j
b0 ?"
b0 B"
b1000 '
b1000 I
b1000 F"
b110 &
b110 H
b110 K"
b100 %
b100 G
b100 P"
b1000 $
b1000 F
b1000 U"
b110 #
b110 E
b110 Z"
b100 "
b100 D
b100 _"
b10 !
b10 C
b10 d"
b10 S
b10 c"
b1 c
b1 b"
b0 8
b0 B
b0 %"
b0 4
b0 >
b0 Q"
19
#100000
09
#105000
b100 !
b100 C
b100 d"
b110 "
b110 D
b110 _"
b1000 #
b1000 E
b1000 Z"
b0 V
b0 T"
b0 f
b0 S"
b0 V"
b110 %
b110 G
b110 P"
b1000 &
b1000 H
b1000 K"
b0 Y
b0 E"
b0 W"
b0 i
b0 D"
b0 G"
b1000 )
b1000 K
b1000 <"
b0 \
b0 6"
b0 H"
b0 l
b0 5"
b0 8"
b0 _
b0 '"
b0 9"
b0 o
b0 &"
19
#110000
09
#115000
b0 [
b0 ;"
b0 M"
b0 k
b0 :"
b0 X
b0 J"
b0 \"
b0 h
b0 I"
b0 L"
b1000 %
b1000 G
b1000 P"
b0 U
b0 Y"
b0 e
b0 X"
b0 ["
b1000 "
b1000 D
b1000 _"
b110 !
b110 C
b110 d"
19
#120000
09
#125000
b1000 !
b1000 C
b1000 d"
b0 T
b0 ^"
b0 d
b0 ]"
b0 `"
b0 W
b0 O"
b0 a"
b0 g
b0 N"
19
#130000
09
#135000
b0 S
b0 c"
b0 c
b0 b"
19
